{"data":{"actionText":"When were vital signs taken (Day 1)","contentText":"Remember to check both the vital signs chart and within the patient file\n\nRemember to use the 24 hr clock - am is on the inside, pm is on the outside of the clock","createdAt":1591880352258,"metadata":{"fields":[{"confidential":false,"dataType":"number","key":"D1FreqMon","label":"Frequency of monitoring of vital signs (Day 1)","optional":false,"position":1,"type":"number"},{"condition":"$D1FreqMon > 0","confidential":false,"dataType":"time","key":"D1Time1","label":"Time of 1st vital signs (Day 1)","optional":false,"position":2,"type":"time"},{"condition":"$D1FreqMon > 1","confidential":false,"dataType":"time","key":"D1Time2","label":"Time of 2nd vital signs (Day 1)","optional":false,"position":3,"type":"time"},{"condition":"$D1FreqMon > 2","confidential":false,"dataType":"time","key":"D1Time3","label":"Time of 3rd vital signs (Day 1)","optional":false,"position":4,"type":"time"},{"condition":"$D1FreqMon > 3","confidential":false,"dataType":"time","key":"D1Time4","label":"Time of 4th vital signs (Day 1)","optional":false,"position":5,"type":"time"},{"condition":"$D1FreqMon > 4","confidential":false,"dataType":"time","key":"D1Time5","label":"Time of 5th vital signs (Day 1)","optional":false,"position":6,"type":"time"},{"condition":"$D1FreqMon > 5","confidential":false,"dataType":"time","key":"D1Time6","label":"Time of 6th vital signs (Day 1)","optional":false,"position":7,"type":"time"}]},"position":3,"refId":"Day 1 timings","screenId":"-LfhpXWTjuiliQ9Qnqk4","scriptId":"-LAeXX-JCxWLkIrQxVLD","sectionTitle":"Time of vital signs (Day 1)","source":"editor","title":"Day 1 time of vital signs","type":"form","updatedAt":1591880352258},"id":228,"screen_id":"-LfhpXWTjuiliQ9Qnqk4","type":"form","position":3,"script_id":"-LAeXX-JCxWLkIrQxVLD","deletedAt":null,"createdAt":"2021-02-02T14:02:10.148Z","updatedAt":"2021-02-02T16:20:38.017Z"}