{"data":{"actionText":"TEMPERATURE","condition":"","createdAt":1602237914714,"data":{"actionText":"TEMPERATURE","createdAt":1603367503910,"epicId":"1.5f","metadata":{"fields":[{"confidential":false,"dataType":"number","format":"#","key":"Temperature","label":"Temperature (degs C)","maxValue":"42","minValue":"30","optional":false,"position":1,"type":"number"}]},"position":21,"refId":"Temp2","screenId":"-MJBo_OX0ii7IqUsPVAe","scriptId":"-MJBnoLY0YLDqLUhPgkK","script_id":"-MJBnoLY0YLDqLUhPgkK","sectionTitle":"Vital SIgns","source":"editor","step":"3/5","storyId":"VS3","title":"VITAL SIGNS","type":"form","updatedAt":1561016422332},"epicId":"1.5f","id":522,"metadata":{"fields":[{"confidential":false,"dataType":"number","format":"#","key":"Temperature","label":"Temperature (degs C)","maxValue":"42","minValue":"30","optional":true,"position":1,"type":"number"}]},"position":21,"refId":"Temp2","screenId":"-MJBo_OX0ii7IqUsPVAe","screen_id":"-MJBo_OX0ii7IqUsPVAe","scriptId":"-MJBnoLY0YLDqLUhPgkK","script_id":"-MJBnoLY0YLDqLUhPgkK","sectionTitle":"Vital SIgns","source":"editor","step":"3/5","storyId":"VS3","title":"VITAL SIGNS","type":"form","updatedAt":1603367503910},"id":282,"screen_id":"-MJBo_OX0ii7IqUsPVAe","type":"form","position":21,"script_id":"-MJBnoLY0YLDqLUhPgkK","deletedAt":null,"createdAt":"2021-02-02T14:02:10.363Z","updatedAt":"2021-03-08T14:33:30.960Z"}