{"data":{"actionText":"Gastroschisis","condition":"$Diagnoses = 'GSch'","contentText":"Warmth and fluids are very important.\nContact surgeons for ongoing management plan","createdAt":1602237915262,"metadata":{"dataType":"void","text1":"Enclose intestines in a plastic glove to minimise fluid loss\n\nDO NOT use warm wet saline packs.","text2":"Use the below as appropriate:\nClothes, hat, bootees\nWarm incubator\nKangaroo (between mother's breasts and wrapped with towels and blanket\n","text3":"10% dextrose infusion as maintenance fluids\nMonitor blood glucose\nNil by mouth\nNG tube on free drainage with frequent aspiration","title1":"Intestines","title2":"Warmth","title3":"Fluids"},"position":142,"refId":"Gastroschisis","screenId":"-MJBo_Q1_zzaunG3BfQd","scriptId":"-MJBnoLY0YLDqLUhPgkK","script_id":"-MJBnoLY0YLDqLUhPgkK","source":"editor","title":"EMERGENCY MANAGEMENT","type":"management","updatedAt":1603367504251},"id":402,"screen_id":"-MJBo_Q1_zzaunG3BfQd","type":"management","position":142,"script_id":"-MJBnoLY0YLDqLUhPgkK","deletedAt":null,"createdAt":"2021-02-02T14:02:10.735Z","updatedAt":"2021-03-08T14:33:30.979Z"}