{"data":{"actionText":"Other Medications","condition":"$MEDSDIS = 'OTH'","contentText":"Any other medications on discharge?","createdAt":1591880352942,"metadata":{"fields":[{"confidential":false,"dataType":"string","key":"MEDSDISOTH","label":"Other medications on discharge","optional":false,"position":1,"type":"text"}]},"position":39,"refId":"Oth meds on disch","screenId":"-LPLxveuebyIkOG3G_mt","scriptId":"-ZYDiO2BTM4kSGZDVXAO","script_id":"-ZYDiO2BTM4kSGZDVXAO","sectionTitle":"Other medications on discharge","source":"editor","title":"OTHER DISCHARGE MEDICATIONS","type":"form","updatedAt":1606915703633},"id":500,"screen_id":"-LPLxveuebyIkOG3G_mt","type":"form","position":39,"script_id":"-ZYDiO2BTM4kSGZDVXAO","deletedAt":null,"createdAt":"2021-02-02T14:02:11.165Z","updatedAt":"2021-02-02T14:02:11.165Z"}