{"data":{"condition":"($BC = true) and ($BC1R = 'BS' or $BC1R = 'CONS' or $BC1R = 'EC' or $BC1R = 'GBS' or $BC1R = 'GDS' or $BC1R = 'KP' or $BC1R = 'PA' or $BC1R = 'SA' or $BC1R = 'LFC' or $BC1R = 'NLFC' or $BC1R = 'OGN' or $BC1R = 'OGP' or $BC1R = 'OTH')","contentText":"If more than one isolate was found, please document name, sensitivities and resistances of additional organisms in free text below. ","createdAt":1591880353059,"metadata":{"fields":[{"confidential":false,"dataType":"number","key":"BCIsol","label":"How many isolates were found?","maxValue":"3","minValue":"0","optional":false,"position":1,"type":"number"},{"condition":"$BCIsol > 1","confidential":false,"dataType":"string","key":"BCSecondIsol","label":"Additional Isolate and sensitivities","optional":false,"position":2,"type":"text"}]},"position":16,"refId":"BC cont","screenId":"-LnMt_1445fRVU7xVbDh","scriptId":"-ZYDiO2BTM4kSGZDVXAO","script_id":"-ZYDiO2BTM4kSGZDVXAO","sectionTitle":"Blood Culture second isolate","source":"editor","title":"Blood Culture Cont","type":"form","updatedAt":1606915703393},"id":524,"screen_id":"-LnMt_1445fRVU7xVbDh","type":"form","position":16,"script_id":"-ZYDiO2BTM4kSGZDVXAO","deletedAt":null,"createdAt":"2021-02-02T14:02:11.218Z","updatedAt":"2021-02-02T14:02:11.218Z"}